ngsidekick/__init__.py
ngsidekick/cors_server.py
ngsidekick/gcs.py
ngsidekick/ngvideo_helper.py
ngsidekick/py.typed
ngsidekick/segmentcolors.py
ngsidekick/state_utils.py
ngsidekick/annotations/__init__.py
ngsidekick/annotations/local.py
ngsidekick/annotations/util.py
ngsidekick/annotations/precomputed/__init__.py
ngsidekick/annotations/precomputed/_id.py
ngsidekick/annotations/precomputed/_relationships.py
ngsidekick/annotations/precomputed/_spatial.py
ngsidekick/annotations/precomputed/_util.py
ngsidekick/annotations/precomputed/_write_buffers.py
ngsidekick/annotations/precomputed/compressed_morton.py
ngsidekick/annotations/precomputed/precomputed.py
ngsidekick/bin/__init__.py
ngsidekick/bin/cors_webserver.py
ngsidekick/segmentprops/__init__.py
ngsidekick/segmentprops/segmentprops.py
ngsidekick/segmentprops/select_segment_properties.py
ngsidekick-0.0.7.dist-info/METADATA
ngsidekick-0.0.7.dist-info/WHEEL
ngsidekick-0.0.7.dist-info/entry_points.txt
ngsidekick-0.0.7.dist-info/licenses/LICENSE
ngsidekick-0.0.7.dist-info/RECORD
