Metadata-Version: 2.4
Name: ngsidekick
Version: 0.0.7
Summary: Tools for neuroglancer scenes.
Project-URL: Homepage, https://github.com/janelia-flyem/ngsidekick
Project-URL: Repository, https://github.com/janelia-flyem/ngsidekick
Project-URL: Issues, https://github.com/janelia-flyem/ngsidekick/issues
Author-email: Stuart Berg <bergs@janelia.hhmi.org>
License: Copyright 2025 HHMI.  All rights reserved.
License-File: LICENSE
Keywords: connectomics,neuroglancer,visualization
Classifier: License :: OSI Approved :: BSD License
Classifier: Programming Language :: Python :: 3
Classifier: Programming Language :: Python :: 3 :: Only
Classifier: Programming Language :: Python :: 3.10
Classifier: Programming Language :: Python :: 3.11
Classifier: Programming Language :: Python :: 3.12
Classifier: Programming Language :: Python :: 3.13
Classifier: Programming Language :: Python :: 3.14
Requires-Python: >=3.10
Requires-Dist: flask
Requires-Dist: neuroglancer
Requires-Dist: numba
Requires-Dist: numpy
Requires-Dist: pandas
Requires-Dist: requests
Requires-Dist: tensorstore
Requires-Dist: tqdm
Provides-Extra: docs
Requires-Dist: myst-parser; extra == 'docs'
Requires-Dist: sphinx-autodoc-typehints; extra == 'docs'
Requires-Dist: sphinx-piccolo-theme; extra == 'docs'
Requires-Dist: sphinx>=7.0; extra == 'docs'
Provides-Extra: gcs
Requires-Dist: google-cloud-storage; extra == 'gcs'
Provides-Extra: test
Requires-Dist: bokeh; extra == 'test'
Requires-Dist: pytest>=7; extra == 'test'
